tree_clipper/__init__.py
tree_clipper/common.py
tree_clipper/dynamic_pointer.py
tree_clipper/export_nodes.py
tree_clipper/id_data_getter.py
tree_clipper/import_nodes.py
tree_clipper/scene_info.py
tree_clipper/specific_abstract.py
tree_clipper/specific_handlers.py
tree_clipper-0.1.1.dist-info/licenses/LICENSE
tree_clipper-0.1.1.dist-info/WHEEL
tree_clipper-0.1.1.dist-info/METADATA
tree_clipper-0.1.1.dist-info/RECORD
